[
    {
        "_id": 12345,
        "Name": "Liam Green",
        "Location": "Sheppard Cineplex",
        "Date": "2021-FEB-09",
        "VerifiedWith": "2nd Dose COVID-19"
    },
    {
        "_id": 12346,
        "Name": "Liam Green",
        "Location": "Fairview Mall",
        "Date": "2021-FEB-10",
        "VerifiedWith": "2nd Dose COVID-19"
    },
    {
        "_id": 12347,
        "Name": "Liam Green",
        "Location": "Dufferin Mall",
        "Date": "2021-FEB-11",
        "VerifiedWith": "2nd Dose COVID-19"
    },
    {
        "_id": 12458,
        "Name": "Ashley Green",
        "Location": "Wallace Espresso",
        "Date": "2021-FEB-01",
        "VerifiedWith": "2nd Dose COVID-19"
    },
    {
        "_id": 12459,
        "Name": "Ashley Green",
        "Location": "Propeller Coffee",
        "Date": "2021-FEB-07",
        "VerifiedWith": "2nd Dose COVID-19"
    }
]